py_yuclid/__init__.py
py_yuclid/api_default.py
py_yuclid/omni_ar.py
py_yuclid/omni_matcher.py
py_yuclid/py.typed
py_yuclid/yuclid_adapter.py
py_yuclid-3.0.0.data/scripts/yuclid
py_yuclid-3.0.0.dist-info/METADATA
py_yuclid-3.0.0.dist-info/WHEEL
py_yuclid-3.0.0.dist-info/RECORD
py_yuclid-3.0.0.dist-info/licenses/LICENSE
py_yuclid-3.0.0.dist-info/licenses/NOTICE.md
