Metadata-Version: 2.4
Name: py-yuclid
Version: 3.0.0
Summary: Python interface to Yuclid geometry solver
Author-Email: Yury Kudryashov <yury@harmonic.fun>, AutoMathis <automathis@protonmail.com>
License-Expression: Apache-2.0
License-File: LICENSE
License-File: NOTICE.md
Classifier: Intended Audience :: Science/Research
Classifier: Intended Audience :: Developers
Classifier: Topic :: Software Development
Classifier: Topic :: Scientific/Engineering
Classifier: Operating System :: Microsoft :: Windows
Classifier: Operating System :: POSIX
Classifier: Operating System :: Unix
Classifier: Operating System :: MacOS
Project-URL: Homepage, https://github.com/Newclid/Newclid/tree/main/yuclid
Project-URL: Repository, https://github.com/Newclid/Newclid.git
Requires-Dist: newclid>=3.0.0rc0
Requires-Dist: pydantic>=2.11.7
